acr_cloud/__init__.py
acr_cloud/acrcloud.py
acr_cloud-0.1.11.dist-info/WHEEL
acr_cloud-0.1.11.dist-info/METADATA
acr_cloud-0.1.11.dist-info/RECORD
