Metadata-Version: 2.1
Name: acr-cloud
Version: 0.1.11
Summary: acrcloud music recognition wrapper
Home-page: https://www.example.org/
License: MIT
Author: Andriy Orehov
Author-email: andriyorehov@gmail.com
Requires-Python: >=3.5,<4.0
Classifier: License :: OSI Approved :: MIT License
Classifier: Programming Language :: Python :: 3
Classifier: Programming Language :: Python :: 3.5
Classifier: Programming Language :: Python :: 3.6
Classifier: Programming Language :: Python :: 3.7
Classifier: Programming Language :: Python :: 3.8
Requires-Dist: requests (>=2.22,<3.0)
Project-URL: Bug Tracker, https://github.com/Live-Lyrics/acrcloud-py/issues/poetry
Project-URL: Documentation, https://github.com/Live-Lyrics/acrcloud-py/blob/master/README.md/poetry
Project-URL: Repository, https://github.com/andriyor/acrcloud-py
Project-URL: Source, https://github.com/andriyor/acrcloud-py/poetry
